magma_converter/__init__.py
magma_converter/convert.py
magma_converter/database.py
magma_converter/new_trace.py
magma_converter/plot.py
magma_converter/sds.py
magma_converter/search.py
magma_converter/utilities.py
magma_converter/plotly_calplot/__init__.py
magma_converter/plotly_calplot/calplot.py
magma_converter/plotly_calplot/date_extractors.py
magma_converter/plotly_calplot/layout_formatter.py
magma_converter/plotly_calplot/raw_heatmap.py
magma_converter/plotly_calplot/single_year_calplot.py
magma_converter/plotly_calplot/utils.py
magma_converter-1.9.4.dist-info/licenses/LICENSE
magma_converter-1.9.4.dist-info/WHEEL
magma_converter-1.9.4.dist-info/METADATA
magma_converter-1.9.4.dist-info/RECORD
