Metadata-Version: 2.4
Name: magma-converter
Version: 1.9.4
Summary: Convert CVGHM seismic data structures into SDS format.
Keywords: seismic,volcano,volcanology,convert,sds,seiscomp,mseed
Author-email: Martanto <martanto@live.com>, Devy Kamil Syahbana <devy.syahbana@gmail.com>, Syarif Abdul Manaf <riefmof@gmail.com>
Requires-Python: >=3.11
Classifier: License :: OSI Approved :: MIT License
Classifier: Operating System :: OS Independent
Classifier: Programming Language :: Python :: 3.11
Classifier: Programming Language :: Python :: 3.12
License-File: LICENSE
Requires-Dist: obspy>=1.4.2
Requires-Dist: openpyxl>=3.1.5
Requires-Dist: pandas>=2.2.2
Requires-Dist: numpy>=2.2.5
Requires-Dist: matplotlib>=3.9.0
Requires-Dist: magma-database>=1.5.0
Requires-Dist: peewee>=3.17.5
Requires-Dist: seaborn>=0.13.0
Requires-Dist: python-dotenv>=1.0.1
Requires-Dist: pytz>=2024.1
Requires-Dist: kaleido
Requires-Dist: plotly>=5.23.0
Requires-Dist: tqdm>=4.67.0
Requires-Dist: ipywidgets>=8.1.5
Requires-Dist: obspy ; extra == "base"
Requires-Dist: openpyxl ; extra == "base"
Requires-Dist: pandas ; extra == "base"
Requires-Dist: numpy ; extra == "base"
Requires-Dist: matplotlib ; extra == "base"
Requires-Dist: magma-database ; extra == "base"
Requires-Dist: peewee ; extra == "base"
Requires-Dist: seaborn ; extra == "base"
Requires-Dist: python-dotenv ; extra == "base"
Requires-Dist: pytz ; extra == "base"
Requires-Dist: kaleido ; extra == "base"
Requires-Dist: plotly ; extra == "base"
Requires-Dist: tqdm ; extra == "base"
Requires-Dist: ipywidgets ; extra == "base"
Project-URL: Homepage, https://github.com/martanto/magma-converter
Project-URL: Issues, https://github.com/martanto/magma-converter/issues
Provides-Extra: base
